tcutils/__init__.py
tcutils/adapters.py
tcutils/cli.py
tcutils/config.py
tcutils/const.py
tcutils/fs.py
tcutils/funcutils.py
tcutils/package.py
tcutils/paths.py
tcutils/schema.py
tcutils/types.py
tcutils/user.py
tcutils/yamlinclude.py
tests/adapters/__init__.py
tests/adapters/someadapter.py
tests/adapters/test_adapters.py
tests/cli/__init__.py
tests/cli/test_cli.py
tests/config/__init__.py
tests/config/test_config.py
tests/fs/__init__.py
tests/fs/test_fs.py
tests/funcutils/__init__.py
tests/funcutils/test_funcutils.py
tests/package/__init__.py
tests/package/test_package.py
tests/paths/__init__.py
tests/paths/test_paths_posix.py
tests/paths/test_paths_windows.py
tests/user/__init__.py
tests/user/test_user.py
tests/yamlinclude/__init__.py
tests/yamlinclude/test_yamlinclude.py
tcutils-0.2.3.dist-info/LICENSE
tcutils-0.2.3.dist-info/METADATA
tcutils-0.2.3.dist-info/WHEEL
tcutils-0.2.3.dist-info/top_level.txt
tcutils-0.2.3.dist-info/RECORD
