Metadata-Version: 2.1
Name: tcutils
Version: 0.2.3
Summary: TropiCoders Utility Library
Home-page: https://github.com/ktomala/tcutils
Author: Karol Tomala
Author-email: ktomala@tropicoders.pl
License: MPL 2.0
Platform: UNKNOWN
Classifier: License :: OSI Approved :: Mozilla Public License 2.0 (MPL 2.0)
Classifier: Programming Language :: Python :: 3
Classifier: Programming Language :: Python :: 3.6
Requires-Python: >=3.6
Requires-Dist: pyyaml
Requires-Dist: marshmallow
Requires-Dist: click
